<annotation>
  <folder>JPEGImages</folder>
  <filename>VOC2007/JPEGImages/004113.jpg</filename>
  <size>
    <width>500</width>
    <height>305</height>
    <depth>3</depth>
  </size>
  <object>
    <name>pedestrians</name>
    <difficult>0</difficult>
    <bndbox>
      <xmin>13</xmin>
      <ymin>149</ymin>
      <xmax>51</xmax>
      <ymax>243</ymax>
    </bndbox>
    <pose>Unspecified</pose>
    <truncated>0</truncated>
  </object>
  <object>
    <name>pedestrians</name>
    <difficult>0</difficult>
    <bndbox>
      <xmin>42</xmin>
      <ymin>139</ymin>
      <xmax>84</xmax>
      <ymax>242</ymax>
    </bndbox>
    <pose>Unspecified</pose>
    <truncated>0</truncated>
  </object>
  <object>
    <name>pedestrians</name>
    <difficult>0</difficult>
    <bndbox>
      <xmin>75</xmin>
      <ymin>141</ymin>
      <xmax>113</xmax>
      <ymax>235</ymax>
    </bndbox>
    <pose>Unspecified</pose>
    <truncated>0</truncated>
  </object>
  <object>
    <name>pedestrians</name>
    <difficult>0</difficult>
    <bndbox>
      <xmin>119</xmin>
      <ymin>152</ymin>
      <xmax>150</xmax>
      <ymax>230</ymax>
    </bndbox>
    <pose>Unspecified</pose>
    <truncated>0</truncated>
  </object>
  <object>
    <name>pedestrians</name>
    <difficult>0</difficult>
    <bndbox>
      <xmin>142</xmin>
      <ymin>142</ymin>
      <xmax>176</xmax>
      <ymax>227</ymax>
    </bndbox>
    <pose>Unspecified</pose>
    <truncated>0</truncated>
  </object>
  <object>
    <name>pedestrians</name>
    <difficult>0</difficult>
    <bndbox>
      <xmin>176</xmin>
      <ymin>146</ymin>
      <xmax>208</xmax>
      <ymax>225</ymax>
    </bndbox>
    <pose>Unspecified</pose>
    <truncated>0</truncated>
  </object>
  <object>
    <name>pedestrians</name>
    <difficult>0</difficult>
    <bndbox>
      <xmin>208</xmin>
      <ymin>147</ymin>
      <xmax>240</xmax>
      <ymax>226</ymax>
    </bndbox>
    <pose>Unspecified</pose>
    <truncated>0</truncated>
  </object>
  <object>
    <name>pedestrians</name>
    <difficult>0</difficult>
    <bndbox>
      <xmin>244</xmin>
      <ymin>140</ymin>
      <xmax>278</xmax>
      <ymax>225</ymax>
    </bndbox>
    <pose>Unspecified</pose>
    <truncated>0</truncated>
  </object>
  <object>
    <name>pedestrians</name>
    <difficult>0</difficult>
    <bndbox>
      <xmin>276</xmin>
      <ymin>140</ymin>
      <xmax>309</xmax>
      <ymax>221</ymax>
    </bndbox>
    <pose>Unspecified</pose>
    <truncated>0</truncated>
  </object>
  <object>
    <name>pedestrians</name>
    <difficult>0</difficult>
    <bndbox>
      <xmin>301</xmin>
      <ymin>137</ymin>
      <xmax>336</xmax>
      <ymax>222</ymax>
    </bndbox>
    <pose>Unspecified</pose>
    <truncated>0</truncated>
  </object>
  <object>
    <name>pedestrians</name>
    <difficult>0</difficult>
    <bndbox>
      <xmin>330</xmin>
      <ymin>146</ymin>
      <xmax>362</xmax>
      <ymax>225</ymax>
    </bndbox>
    <pose>Unspecified</pose>
    <truncated>0</truncated>
  </object>
  <object>
    <name>pedestrians</name>
    <difficult>0</difficult>
    <bndbox>
      <xmin>353</xmin>
      <ymin>136</ymin>
      <xmax>389</xmax>
      <ymax>223</ymax>
    </bndbox>
    <pose>Unspecified</pose>
    <truncated>0</truncated>
  </object>
  <object>
    <name>pedestrians</name>
    <difficult>0</difficult>
    <bndbox>
      <xmin>381</xmin>
      <ymin>149</ymin>
      <xmax>414</xmax>
      <ymax>231</ymax>
    </bndbox>
    <pose>Unspecified</pose>
    <truncated>0</truncated>
  </object>
  <object>
    <name>pedestrians</name>
    <difficult>0</difficult>
    <bndbox>
      <xmin>415</xmin>
      <ymin>142</ymin>
      <xmax>449</xmax>
      <ymax>228</ymax>
    </bndbox>
    <pose>Unspecified</pose>
    <truncated>0</truncated>
  </object>
  <object>
    <name>pedestrians</name>
    <difficult>0</difficult>
    <bndbox>
      <xmin>447</xmin>
      <ymin>150</ymin>
      <xmax>484</xmax>
      <ymax>240</ymax>
    </bndbox>
    <pose>Unspecified</pose>
    <truncated>0</truncated>
  </object>
</annotation>
