<annotation>
  <folder>JPEGImages</folder>
  <filename>VOC2007/JPEGImages/011773.jpg</filename>
  <size>
    <width>690</width>
    <height>923</height>
    <depth>3</depth>
  </size>
  <object>
    <name>pedestrians</name>
    <difficult>0</difficult>
    <bndbox>
      <xmin>1</xmin>
      <ymin>267</ymin>
      <xmax>67</xmax>
      <ymax>439</ymax>
    </bndbox>
    <pose>Unspecified</pose>
    <truncated>0</truncated>
  </object>
  <object>
    <name>pedestrians</name>
    <difficult>0</difficult>
    <bndbox>
      <xmin>34</xmin>
      <ymin>298</ymin>
      <xmax>74</xmax>
      <ymax>395</ymax>
    </bndbox>
    <pose>Unspecified</pose>
    <truncated>0</truncated>
  </object>
  <object>
    <name>pedestrians</name>
    <difficult>0</difficult>
    <bndbox>
      <xmin>72</xmin>
      <ymin>290</ymin>
      <xmax>110</xmax>
      <ymax>382</ymax>
    </bndbox>
    <pose>Unspecified</pose>
    <truncated>0</truncated>
  </object>
  <object>
    <name>pedestrians</name>
    <difficult>0</difficult>
    <bndbox>
      <xmin>151</xmin>
      <ymin>287</ymin>
      <xmax>195</xmax>
      <ymax>395</ymax>
    </bndbox>
    <pose>Unspecified</pose>
    <truncated>0</truncated>
  </object>
  <object>
    <name>pedestrians</name>
    <difficult>0</difficult>
    <bndbox>
      <xmin>131</xmin>
      <ymin>338</ymin>
      <xmax>221</xmax>
      <ymax>560</ymax>
    </bndbox>
    <pose>Unspecified</pose>
    <truncated>0</truncated>
  </object>
  <object>
    <name>pedestrians</name>
    <difficult>0</difficult>
    <bndbox>
      <xmin>197</xmin>
      <ymin>315</ymin>
      <xmax>269</xmax>
      <ymax>494</ymax>
    </bndbox>
    <pose>Unspecified</pose>
    <truncated>0</truncated>
  </object>
  <object>
    <name>pedestrians</name>
    <difficult>0</difficult>
    <bndbox>
      <xmin>239</xmin>
      <ymin>311</ymin>
      <xmax>295</xmax>
      <ymax>450</ymax>
    </bndbox>
    <pose>Unspecified</pose>
    <truncated>0</truncated>
  </object>
  <object>
    <name>pedestrians</name>
    <difficult>0</difficult>
    <bndbox>
      <xmin>265</xmin>
      <ymin>302</ymin>
      <xmax>317</xmax>
      <ymax>431</ymax>
    </bndbox>
    <pose>Unspecified</pose>
    <truncated>0</truncated>
  </object>
  <object>
    <name>pedestrians</name>
    <difficult>0</difficult>
    <bndbox>
      <xmin>279</xmin>
      <ymin>302</ymin>
      <xmax>328</xmax>
      <ymax>423</ymax>
    </bndbox>
    <pose>Unspecified</pose>
    <truncated>0</truncated>
  </object>
  <object>
    <name>pedestrians</name>
    <difficult>0</difficult>
    <bndbox>
      <xmin>296</xmin>
      <ymin>299</ymin>
      <xmax>339</xmax>
      <ymax>407</ymax>
    </bndbox>
    <pose>Unspecified</pose>
    <truncated>0</truncated>
  </object>
  <object>
    <name>pedestrians</name>
    <difficult>0</difficult>
    <bndbox>
      <xmin>314</xmin>
      <ymin>298</ymin>
      <xmax>356</xmax>
      <ymax>402</ymax>
    </bndbox>
    <pose>Unspecified</pose>
    <truncated>0</truncated>
  </object>
  <object>
    <name>pedestrians</name>
    <difficult>0</difficult>
    <bndbox>
      <xmin>247</xmin>
      <ymin>384</ymin>
      <xmax>393</xmax>
      <ymax>742</ymax>
    </bndbox>
    <pose>Unspecified</pose>
    <truncated>0</truncated>
  </object>
  <object>
    <name>pedestrians</name>
    <difficult>0</difficult>
    <bndbox>
      <xmin>437</xmin>
      <ymin>362</ymin>
      <xmax>538</xmax>
      <ymax>609</ymax>
    </bndbox>
    <pose>Unspecified</pose>
    <truncated>0</truncated>
  </object>
  <object>
    <name>pedestrians</name>
    <difficult>0</difficult>
    <bndbox>
      <xmin>417</xmin>
      <ymin>332</ymin>
      <xmax>486</xmax>
      <ymax>504</ymax>
    </bndbox>
    <pose>Unspecified</pose>
    <truncated>0</truncated>
  </object>
  <object>
    <name>pedestrians</name>
    <difficult>0</difficult>
    <bndbox>
      <xmin>412</xmin>
      <ymin>310</ymin>
      <xmax>462</xmax>
      <ymax>433</ymax>
    </bndbox>
    <pose>Unspecified</pose>
    <truncated>0</truncated>
  </object>
  <object>
    <name>pedestrians</name>
    <difficult>0</difficult>
    <bndbox>
      <xmin>409</xmin>
      <ymin>304</ymin>
      <xmax>449</xmax>
      <ymax>405</ymax>
    </bndbox>
    <pose>Unspecified</pose>
    <truncated>0</truncated>
  </object>
  <object>
    <name>partially</name>
    <difficult>0</difficult>
    <bndbox>
      <xmin>447</xmin>
      <ymin>324</ymin>
      <xmax>485</xmax>
      <ymax>339</ymax>
    </bndbox>
    <pose>Unspecified</pose>
    <truncated>0</truncated>
  </object>
  <object>
    <name>partially</name>
    <difficult>0</difficult>
    <bndbox>
      <xmin>416</xmin>
      <ymin>296</ymin>
      <xmax>427</xmax>
      <ymax>375</ymax>
    </bndbox>
    <pose>Unspecified</pose>
    <truncated>0</truncated>
  </object>
  <object>
    <name>crowd</name>
    <difficult>0</difficult>
    <bndbox>
      <xmin>122</xmin>
      <ymin>285</ymin>
      <xmax>162</xmax>
      <ymax>303</ymax>
    </bndbox>
    <pose>Unspecified</pose>
    <truncated>0</truncated>
  </object>
  <object>
    <name>crowd</name>
    <difficult>0</difficult>
    <bndbox>
      <xmin>206</xmin>
      <ymin>295</ymin>
      <xmax>226</xmax>
      <ymax>306</ymax>
    </bndbox>
    <pose>Unspecified</pose>
    <truncated>0</truncated>
  </object>
  <object>
    <name>crowd</name>
    <difficult>0</difficult>
    <bndbox>
      <xmin>348</xmin>
      <ymin>300</ymin>
      <xmax>398</xmax>
      <ymax>316</ymax>
    </bndbox>
    <pose>Unspecified</pose>
    <truncated>0</truncated>
  </object>
  <object>
    <name>crowd</name>
    <difficult>0</difficult>
    <bndbox>
      <xmin>575</xmin>
      <ymin>319</ymin>
      <xmax>690</xmax>
      <ymax>355</ymax>
    </bndbox>
    <pose>Unspecified</pose>
    <truncated>0</truncated>
  </object>
  <object>
    <name>crowd</name>
    <difficult>0</difficult>
    <bndbox>
      <xmin>46</xmin>
      <ymin>286</ymin>
      <xmax>87</xmax>
      <ymax>303</ymax>
    </bndbox>
    <pose>Unspecified</pose>
    <truncated>0</truncated>
  </object>
</annotation>
